CyberGearDashboard/__init__.py
CyberGearDashboard/__main__.py
CyberGearDashboard/app.py
CyberGearDashboard/args_parser.py
CyberGearDashboard/constants.py
CyberGearDashboard/listen.py
CyberGearDashboard/motor_state.py
CyberGearDashboard/watcher.py
CyberGearDashboard/charts/__init__.py
CyberGearDashboard/charts/chart.py
CyberGearDashboard/charts/layout.py
CyberGearDashboard/controller/__init__.py
CyberGearDashboard/controller/abstract_classes.py
CyberGearDashboard/controller/controller_dock.py
CyberGearDashboard/controller/idle_control_panel.py
CyberGearDashboard/controller/operation_control_panel.py
CyberGearDashboard/controller/position_control_panel.py
CyberGearDashboard/controller/slider_input_widgets.py
CyberGearDashboard/controller/torque_control_panel.py
CyberGearDashboard/controller/velocity_control_panel.py
CyberGearDashboard/parameters/__init__.py
CyberGearDashboard/parameters/parameter_dock.py
CyberGearDashboard/parameters/table_model.py
cybergeardashboard-0.2.1.dist-info/METADATA
cybergeardashboard-0.2.1.dist-info/WHEEL
cybergeardashboard-0.2.1.dist-info/licenses/LICENSE
cybergeardashboard-0.2.1.dist-info/RECORD
