Metadata-Version: 2.4
Name: CyberGearDashboard
Version: 0.2.1
Summary: A GUI to control the CyberGear micromotor
Project-URL: Homepage, https://github.com/jgillick/CyberGearDashboard
Project-URL: Issues, https://github.com/jgillick/CyberGearDashboard/issues
Author: Jeremy Gillick
License-Expression: MIT
License-File: LICENSE
Classifier: Operating System :: OS Independent
Classifier: Programming Language :: Python :: 3
Requires-Python: >=3.8
Requires-Dist: cybergeardriver==0.2.0
Requires-Dist: gs-usb==0.3.0
Requires-Dist: pyqtgraph==0.13.7
Requires-Dist: pyside6-addons==6.8.2.1
Requires-Dist: pyside6-essentials==6.8.2.1
Requires-Dist: pyside6==6.8.2.1
Requires-Dist: python-can==4.5.0
